{
  "name": "Krypta",
  "width": 3000,
  "height": 2850,
  "grid": 150,
  "shiftX": 0,
  "shiftY": 0,
  "gridDistance": 5.0,
  "gridUnits": "ft",
  "padding": 0.0,
  "gridColor": "#000000",
  "gridAlpha": 0.2,
  "globalLight": true,
  "darkness": 0.0,
  "lights": [],
  "walls": [
    {
      "c": [
        528,
        2315,
        2472,
        2315
      ],
      "move": 1,
      "sense": 1,
      "sound": 1,
      "door": 0
    },
    {
      "c": [
        528,
        2315,
        528,
        1019
      ],
      "move": 1,
      "sense": 1,
      "sound": 1,
      "door": 0
    },
    {
      "c": [
        528,
        1019,
        1176,
        1019
      ],
      "move": 1,
      "sense": 1,
      "sound": 1,
      "door": 0
    },
    {
      "c": [
        1178,
        1021,
        1178,
        860
      ],
      "move": 1,
      "sense": 0,
      "sound": 1,
      "door": 0
    },
    {
      "c": [
        1188,
        878,
        1188,
        722
      ],
      "move": 1,
      "sense": 0,
      "sound": 1,
      "door": 0
    },
    {
      "c": [
        1178,
        699,
        1178,
        538
      ],
      "move": 1,
      "sense": 0,
      "sound": 1,
      "door": 0
    },
    {
      "c": [
        1176,
        533,
        1824,
        533
      ],
      "move": 1,
      "sense": 1,
      "sound": 1,
      "door": 0
    },
    {
      "c": [
        1824,
        1019,
        1824,
        857
      ],
      "move": 1,
      "sense": 1,
      "sound": 1,
      "door": 0
    },
    {
      "c": [
        1824,
        1019,
        2472,
        1019
      ],
      "move": 1,
      "sense": 1,
      "sound": 1,
      "door": 0
    },
    {
      "c": [
        1822,
        860,
        1822,
        699
      ],
      "move": 1,
      "sense": 0,
      "sound": 1,
      "door": 0
    },
    {
      "c": [
        1824,
        695,
        1824,
        533
      ],
      "move": 1,
      "sense": 1,
      "sound": 1,
      "door": 0
    },
    {
      "c": [
        2472,
        2315,
        2472,
        1019
      ],
      "move": 1,
      "sense": 1,
      "sound": 1,
      "door": 0
    },
    {
      "c": [
        1178,
        1021,
        1176,
        1019
      ],
      "move": 1,
      "sense": 1,
      "sound": 1,
      "door": 0
    },
    {
      "c": [
        1188,
        878,
        1178,
        860
      ],
      "move": 1,
      "sense": 0,
      "sound": 1,
      "door": 0
    },
    {
      "c": [
        1188,
        722,
        1178,
        699
      ],
      "move": 1,
      "sense": 0,
      "sound": 1,
      "door": 0
    },
    {
      "c": [
        1178,
        538,
        1176,
        533
      ],
      "move": 1,
      "sense": 1,
      "sound": 1,
      "door": 0
    },
    {
      "c": [
        1822,
        860,
        1824,
        857
      ],
      "move": 1,
      "sense": 1,
      "sound": 1,
      "door": 0
    },
    {
      "c": [
        1822,
        699,
        1824,
        695
      ],
      "move": 1,
      "sense": 1,
      "sound": 1,
      "door": 0
    },
    {
      "c": [
        949,
        1445,
        917,
        1445
      ],
      "move": 1,
      "sense": 2,
      "sound": 1,
      "door": 0
    },
    {
      "c": [
        930,
        1450,
        907,
        1427
      ],
      "move": 1,
      "sense": 2,
      "sound": 1,
      "door": 0
    },
    {
      "c": [
        912,
        1440,
        912,
        1408
      ],
      "move": 1,
      "sense": 2,
      "sound": 1,
      "door": 0
    },
    {
      "c": [
        907,
        1421,
        930,
        1398
      ],
      "move": 1,
      "sense": 2,
      "sound": 1,
      "door": 0
    },
    {
      "c": [
        917,
        1403,
        949,
        1403
      ],
      "move": 1,
      "sense": 2,
      "sound": 1,
      "door": 0
    },
    {
      "c": [
        936,
        1398,
        959,
        1421
      ],
      "move": 1,
      "sense": 2,
      "sound": 1,
      "door": 0
    },
    {
      "c": [
        954,
        1408,
        954,
        1440
      ],
      "move": 1,
      "sense": 2,
      "sound": 1,
      "door": 0
    },
    {
      "c": [
        959,
        1427,
        936,
        1450
      ],
      "move": 1,
      "sense": 2,
      "sound": 1,
      "door": 0
    },
    {
      "c": [
        2083,
        1445,
        2051,
        1445
      ],
      "move": 1,
      "sense": 2,
      "sound": 1,
      "door": 0
    },
    {
      "c": [
        2064,
        1450,
        2041,
        1427
      ],
      "move": 1,
      "sense": 2,
      "sound": 1,
      "door": 0
    },
    {
      "c": [
        2046,
        1440,
        2046,
        1408
      ],
      "move": 1,
      "sense": 2,
      "sound": 1,
      "door": 0
    },
    {
      "c": [
        2041,
        1421,
        2064,
        1398
      ],
      "move": 1,
      "sense": 2,
      "sound": 1,
      "door": 0
    },
    {
      "c": [
        2051,
        1403,
        2083,
        1403
      ],
      "move": 1,
      "sense": 2,
      "sound": 1,
      "door": 0
    },
    {
      "c": [
        2070,
        1398,
        2093,
        1421
      ],
      "move": 1,
      "sense": 2,
      "sound": 1,
      "door": 0
    },
    {
      "c": [
        2088,
        1408,
        2088,
        1440
      ],
      "move": 1,
      "sense": 2,
      "sound": 1,
      "door": 0
    },
    {
      "c": [
        2093,
        1427,
        2070,
        1450
      ],
      "move": 1,
      "sense": 2,
      "sound": 1,
      "door": 0
    },
    {
      "c": [
        949,
        2093,
        917,
        2093
      ],
      "move": 1,
      "sense": 2,
      "sound": 1,
      "door": 0
    },
    {
      "c": [
        930,
        2098,
        907,
        2075
      ],
      "move": 1,
      "sense": 2,
      "sound": 1,
      "door": 0
    },
    {
      "c": [
        912,
        2088,
        912,
        2056
      ],
      "move": 1,
      "sense": 2,
      "sound": 1,
      "door": 0
    },
    {
      "c": [
        907,
        2069,
        930,
        2046
      ],
      "move": 1,
      "sense": 2,
      "sound": 1,
      "door": 0
    },
    {
      "c": [
        917,
        2051,
        949,
        2051
      ],
      "move": 1,
      "sense": 2,
      "sound": 1,
      "door": 0
    },
    {
      "c": [
        936,
        2046,
        959,
        2069
      ],
      "move": 1,
      "sense": 2,
      "sound": 1,
      "door": 0
    },
    {
      "c": [
        954,
        2056,
        954,
        2088
      ],
      "move": 1,
      "sense": 2,
      "sound": 1,
      "door": 0
    },
    {
      "c": [
        959,
        2075,
        936,
        2098
      ],
      "move": 1,
      "sense": 2,
      "sound": 1,
      "door": 0
    },
    {
      "c": [
        2091,
        2110,
        2055,
        2110
      ],
      "move": 1,
      "sense": 2,
      "sound": 1,
      "door": 0
    },
    {
      "c": [
        2074,
        2118,
        2049,
        2093
      ],
      "move": 1,
      "sense": 2,
      "sound": 1,
      "door": 0
    },
    {
      "c": [
        2057,
        2112,
        2057,
        2076
      ],
      "move": 1,
      "sense": 2,
      "sound": 1,
      "door": 0
    },
    {
      "c": [
        2049,
        2096,
        2074,
        2071
      ],
      "move": 1,
      "sense": 2,
      "sound": 1,
      "door": 0
    },
    {
      "c": [
        2055,
        2079,
        2091,
        2079
      ],
      "move": 1,
      "sense": 2,
      "sound": 1,
      "door": 0
    },
    {
      "c": [
        2071,
        2071,
        2096,
        2096
      ],
      "move": 1,
      "sense": 2,
      "sound": 1,
      "door": 0
    },
    {
      "c": [
        2088,
        2076,
        2088,
        2112
      ],
      "move": 1,
      "sense": 2,
      "sound": 1,
      "door": 0
    },
    {
      "c": [
        2096,
        2093,
        2071,
        2118
      ],
      "move": 1,
      "sense": 2,
      "sound": 1,
      "door": 0
    }
  ],
  "img": null,
  "foreground": null
}